traylinx_auth_client/__init__.py
traylinx_auth_client/client.py
traylinx_auth_client/config.py
traylinx_auth_client/exceptions.py
traylinx_auth_client/main.py
traylinx_auth_client/services.py
traylinx_auth_client/token_manager.py
traylinx_auth_client-1.0.4.dist-info/METADATA
traylinx_auth_client-1.0.4.dist-info/WHEEL
traylinx_auth_client-1.0.4.dist-info/licenses/LICENSE
traylinx_auth_client-1.0.4.dist-info/RECORD
