Metadata-Version: 2.4
Name: traylinx-auth-client
Version: 1.0.4
Summary: Enterprise-grade authentication client for Traylinx Sentinel API and agent-to-agent communication
License: MIT
License-File: LICENSE
Keywords: traylinx,authentication,a2a,agent2agent,google-a2a,sentinel,oauth2,jwt,agent,microservices,api-client,enterprise
Author: Traylinx
Author-email: dev@traylinx.com
Requires-Python: >=3.8
Classifier: Development Status :: 5 - Production/Stable
Classifier: Intended Audience :: Developers
Classifier: Intended Audience :: System Administrators
Classifier: License :: OSI Approved :: MIT License
Classifier: Operating System :: OS Independent
Classifier: Programming Language :: Python :: 3
Classifier: Programming Language :: Python :: 3.8
Classifier: Programming Language :: Python :: 3.9
Classifier: Programming Language :: Python :: 3.10
Classifier: Programming Language :: Python :: 3.11
Classifier: Programming Language :: Python :: 3.12
Classifier: Programming Language :: Python :: 3.13
Classifier: Programming Language :: Python :: 3.14
Classifier: Topic :: Internet :: WWW/HTTP :: HTTP Servers
Classifier: Topic :: Security
Classifier: Topic :: Software Development :: Libraries :: Python Modules
Classifier: Topic :: System :: Distributed Computing
Classifier: Typing :: Typed
Requires-Dist: fastapi (>=0.103.2)
Requires-Dist: pydantic (>=2.0.0,<3.0.0)
Requires-Dist: requests (>=2.31.0,<3.0.0)
Project-URL: Documentation, https://docs.traylinx.com/auth-client
Project-URL: Homepage, https://traylinx.com
Project-URL: Repository, https://github.com/traylinx/traylinx-auth-client-py
